{
	"info": {
		"_postman_id": "7d884835-46fd-431a-a065-81f099d24f22",
		"name": "karina",
		"schema": "https://schema.getpostman.com/json/collection/v2.1.0/collection.json"
	},
	"item": [
		{
			"name": "5005",
			"request": {
				"method": "GET",
				"header": [],
				"url": {
					"raw": "http://162.55.220.72:5005/get_method?name=Karina&age=29",
					"protocol": "http",
					"host": [
						"162",
						"55",
						"220",
						"72"
					],
					"port": "5005",
					"path": [
						"get_method"
					],
					"query": [
						{
							"key": "name",
							"value": "Karina"
						},
						{
							"key": "age",
							"value": "29"
						}
					]
				}
			},
			"response": []
		},
		{
			"name": "5005 Copy",
			"request": {
				"method": "GET",
				"header": [],
				"url": {
					"raw": "http://162.55.220.72:5005/get_method?name=Karina&age=29",
					"protocol": "http",
					"host": [
						"162",
						"55",
						"220",
						"72"
					],
					"port": "5005",
					"path": [
						"get_method"
					],
					"query": [
						{
							"key": "name",
							"value": "Karina"
						},
						{
							"key": "age",
							"value": "29"
						}
					]
				}
			},
			"response": []
		},
		{
			"name": "object_info_3",
			"request": {
				"method": "GET",
				"header": [],
				"url": {
					"raw": "http://162.55.220.72:5005/object_info_3?name=Karina&age=29&salary=2000",
					"protocol": "http",
					"host": [
						"162",
						"55",
						"220",
						"72"
					],
					"port": "5005",
					"path": [
						"object_info_3"
					],
					"query": [
						{
							"key": "name",
							"value": "Karina"
						},
						{
							"key": "age",
							"value": "29"
						},
						{
							"key": "salary",
							"value": "2000"
						}
					]
				}
			},
			"response": []
		},
		{
			"name": "object_info_4",
			"request": {
				"method": "GET",
				"header": [],
				"url": {
					"raw": "http://162.55.220.72:5005/object_info_4?name=Karina&age=29&salary=2000",
					"protocol": "http",
					"host": [
						"162",
						"55",
						"220",
						"72"
					],
					"port": "5005",
					"path": [
						"object_info_4"
					],
					"query": [
						{
							"key": "name",
							"value": "Karina"
						},
						{
							"key": "age",
							"value": "29"
						},
						{
							"key": "salary",
							"value": "2000"
						}
					]
				}
			},
			"response": []
		},
		{
			"name": "object_info_2",
			"request": {
				"method": "GET",
				"header": [],
				"url": {
					"raw": "http://162.55.220.72:5005/object_info_2?name=Karina&age=29&salary=2000",
					"protocol": "http",
					"host": [
						"162",
						"55",
						"220",
						"72"
					],
					"port": "5005",
					"path": [
						"object_info_2"
					],
					"query": [
						{
							"key": "name",
							"value": "Karina"
						},
						{
							"key": "age",
							"value": "29"
						},
						{
							"key": "salary",
							"value": "2000"
						}
					]
				}
			},
			"response": []
		},
		{
			"name": "post",
			"request": {
				"method": "POST",
				"header": [],
				"body": {
					"mode": "formdata",
					"formdata": [
						{
							"key": "name",
							"value": "Karina",
							"type": "text"
						},
						{
							"key": "age",
							"value": "29",
							"type": "text"
						},
						{
							"key": "salary",
							"value": "2000",
							"type": "text"
						}
					]
				},
				"url": {
					"raw": "http://162.55.220.72:5005/user_info_3",
					"protocol": "http",
					"host": [
						"162",
						"55",
						"220",
						"72"
					],
					"port": "5005",
					"path": [
						"user_info_3"
					]
				}
			},
			"response": []
		},
		{
			"name": "login",
			"request": {
				"method": "POST",
				"header": [],
				"body": {
					"mode": "formdata",
					"formdata": [
						{
							"key": "name",
							"value": "Karina",
							"type": "text"
						},
						{
							"key": "age",
							"value": "29",
							"type": "text"
						},
						{
							"key": "salary",
							"value": "2000",
							"type": "text"
						}
					]
				},
				"url": {
					"raw": "http://162.55.220.72:5005/login?login=karina&password=123456789",
					"protocol": "http",
					"host": [
						"162",
						"55",
						"220",
						"72"
					],
					"port": "5005",
					"path": [
						"login"
					],
					"query": [
						{
							"key": "login",
							"value": "karina"
						},
						{
							"key": "password",
							"value": "123456789"
						}
					]
				}
			},
			"response": []
		},
		{
			"name": "user_info",
			"request": {
				"method": "POST",
				"header": [],
				"body": {
					"mode": "raw",
					"raw": "{\r\n    \"name\":\"karina\",\r\n    \"age\":\"29\",\r\n    \"salary\":\"2000\",\r\n    \"auth_token\":\"/s34lfgbj/None/jjd909/74822kjkWpqc3691None381524evny\"\r\n}",
					"options": {
						"raw": {
							"language": "json"
						}
					}
				},
				"url": {
					"raw": "http://162.55.220.72:5005/user_info",
					"protocol": "http",
					"host": [
						"162",
						"55",
						"220",
						"72"
					],
					"port": "5005",
					"path": [
						"user_info"
					]
				}
			},
			"response": [
				{
					"name": "user_info",
					"originalRequest": {
						"method": "POST",
						"header": [],
						"body": {
							"mode": "raw",
							"raw": "{\r\n    \"name\":\"karina\",\r\n    \"age\":\"29\",\r\n    \"salary\":\"2000\",\r\n    \"auth_token\":\"/s34lfgbj/None/jjd909/74822kjkWpqc3691None381524evny\"\r\n}",
							"options": {
								"raw": {
									"language": "json"
								}
							}
						},
						"url": {
							"raw": "http://162.55.220.72:5005/user_info",
							"protocol": "http",
							"host": [
								"162",
								"55",
								"220",
								"72"
							],
							"port": "5005",
							"path": [
								"user_info"
							]
						}
					},
					"status": "OK",
					"code": 200,
					"_postman_previewlanguage": "json",
					"header": [
						{
							"key": "Content-Type",
							"value": "application/json"
						},
						{
							"key": "Content-Length",
							"value": "238"
						},
						{
							"key": "Server",
							"value": "Werkzeug/2.0.1 Python/3.8.10"
						},
						{
							"key": "Date",
							"value": "Fri, 13 May 2022 08:14:40 GMT"
						}
					],
					"cookie": [],
					"body": "{\n    \"person\": {\n        \"u_age\": 29,\n        \"u_name\": [\n            \"karina\",\n            2000,\n            29\n        ],\n        \"u_salary_1_5_year\": 8000\n    },\n    \"qa_salary_after_12_months\": 5800,\n    \"qa_salary_after_6_months\": 4000,\n    \"start_qa_salary\": 2000\n}"
				}
			]
		},
		{
			"name": "user_info_2",
			"request": {
				"method": "POST",
				"header": [],
				"body": {
					"mode": "formdata",
					"formdata": [
						{
							"key": "name",
							"value": "Karina",
							"type": "text"
						},
						{
							"key": "age",
							"value": "29",
							"type": "text"
						},
						{
							"key": "salary",
							"value": "2000",
							"type": "text"
						}
					]
				},
				"url": {
					"raw": "http://162.55.220.72:5005/user_info_2",
					"protocol": "http",
					"host": [
						"162",
						"55",
						"220",
						"72"
					],
					"port": "5005",
					"path": [
						"user_info_2"
					]
				}
			},
			"response": []
		},
		{
			"name": "object_info_1",
			"request": {
				"method": "GET",
				"header": [],
				"url": {
					"raw": "http://162.55.220.72:5005/object_info_1?name=Karina&age=29&weight=50",
					"protocol": "http",
					"host": [
						"162",
						"55",
						"220",
						"72"
					],
					"port": "5005",
					"path": [
						"object_info_1"
					],
					"query": [
						{
							"key": "name",
							"value": "Karina"
						},
						{
							"key": "age",
							"value": "29"
						},
						{
							"key": "weight",
							"value": "50"
						}
					]
				}
			},
			"response": []
		}
	]
}